CHANGES.rst
MANIFEST.in
README.rst
setup.cfg
setup.py
version.txt
src/metapensiero/__init__.py
src/metapensiero.signal.egg-info/PKG-INFO
src/metapensiero.signal.egg-info/SOURCES.txt
src/metapensiero.signal.egg-info/dependency_links.txt
src/metapensiero.signal.egg-info/namespace_packages.txt
src/metapensiero.signal.egg-info/requires.txt
src/metapensiero.signal.egg-info/top_level.txt
src/metapensiero/signal/__init__.py
src/metapensiero/signal/atom.py
src/metapensiero/signal/external.py
src/metapensiero/signal/user.py
src/metapensiero/signal/weak.py