Metadata-Version: 1.1
Name: metapensiero.signal
Version: 0.9
Summary: A event framework that is asyncio aware
Home-page: https://github.com/azazel75/metapensiero.signal
Author: Alberto Berti
Author-email: alberto@metapensiero.it
License: GPLv3+
Keywords: signal event asyncio framework
Platform: UNKNOWN
Classifier: Development Status :: 5 - Production/Stable
Classifier: Programming Language :: Python
Classifier: Programming Language :: Python :: 3
Classifier: Programming Language :: Python :: 3.4
Classifier: Programming Language :: Python :: 3.5
Classifier: Programming Language :: Python :: 2
Classifier: Programming Language :: Python :: 2.7
Classifier: Intended Audience :: Developers
Classifier: License :: OSI Approved :: GNU General Public License (GPL)
